README.rst
setup.py
sqlalchemy_pytest_fixtures.py
sqlalchemy_pytest_fixtures.egg-info/PKG-INFO
sqlalchemy_pytest_fixtures.egg-info/SOURCES.txt
sqlalchemy_pytest_fixtures.egg-info/dependency_links.txt
sqlalchemy_pytest_fixtures.egg-info/requires.txt
sqlalchemy_pytest_fixtures.egg-info/top_level.txt